Metadata-Version: 1.0
Name: ARIC
Version: 1.0.0
Summary: ARIC: Accurate and robust inference of cell type proportions from bulk gene expression or DNA methylation data
Home-page: https://xwanglabthu.github.io/ARIC/
Author: Wei Zhang, Hanwen Xu
Author-email: w-zhang16@mails.tsinghua.edu.cn, xuhw20@mails.tsinghua.edu.cn
License: GPL V3
Keywords: pip,ARIC
Platform: any
